TutorialspointJavaJishuJiaocheng20160127Fix1/README.md
TutorialspointJavaJishuJiaocheng20160127Fix1/__init__.py
TutorialspointJavaJishuJiaocheng20160127Fix1/__main__.py
TutorialspointJavaJishuJiaocheng20160127Fix1/file.epub
TutorialspointJavaJishuJiaocheng20160127Fix1/index.html
TutorialspointJavaJishuJiaocheng20160127Fix1/css/__init__.py
TutorialspointJavaJishuJiaocheng20160127Fix1/css/annotations.css
TutorialspointJavaJishuJiaocheng20160127Fix1/css/main.css
TutorialspointJavaJishuJiaocheng20160127Fix1/css/normalize.css
TutorialspointJavaJishuJiaocheng20160127Fix1/css/popup.css
TutorialspointJavaJishuJiaocheng20160127Fix1/font/__init__.py
TutorialspointJavaJishuJiaocheng20160127Fix1/font/fontello.eot
TutorialspointJavaJishuJiaocheng20160127Fix1/font/fontello.svg
TutorialspointJavaJishuJiaocheng20160127Fix1/font/fontello.ttf
TutorialspointJavaJishuJiaocheng20160127Fix1/font/fontello.woff
TutorialspointJavaJishuJiaocheng20160127Fix1/img/__init__.py
TutorialspointJavaJishuJiaocheng20160127Fix1/img/annotator-glyph-sprite.png
TutorialspointJavaJishuJiaocheng20160127Fix1/img/annotator-icon-sprite.png
TutorialspointJavaJishuJiaocheng20160127Fix1/img/apple-touch-icon.png
TutorialspointJavaJishuJiaocheng20160127Fix1/img/cancelfullscreen.png
TutorialspointJavaJishuJiaocheng20160127Fix1/img/close.png
TutorialspointJavaJishuJiaocheng20160127Fix1/img/fullscreen.png
TutorialspointJavaJishuJiaocheng20160127Fix1/img/loader.gif
TutorialspointJavaJishuJiaocheng20160127Fix1/img/menu-icon.png
TutorialspointJavaJishuJiaocheng20160127Fix1/img/save.png
TutorialspointJavaJishuJiaocheng20160127Fix1/img/saved.png
TutorialspointJavaJishuJiaocheng20160127Fix1/img/settings-s.png
TutorialspointJavaJishuJiaocheng20160127Fix1/img/settings.png
TutorialspointJavaJishuJiaocheng20160127Fix1/img/star.png
TutorialspointJavaJishuJiaocheng20160127Fix1/js/__init__.py
TutorialspointJavaJishuJiaocheng20160127Fix1/js/epub.js
TutorialspointJavaJishuJiaocheng20160127Fix1/js/epub.min.js
tutorialspoint_java_jishu_jiaocheng_20160127_fix1-2024.3.2.0.dist-info/METADATA
tutorialspoint_java_jishu_jiaocheng_20160127_fix1-2024.3.2.0.dist-info/WHEEL
tutorialspoint_java_jishu_jiaocheng_20160127_fix1-2024.3.2.0.dist-info/entry_points.txt
tutorialspoint_java_jishu_jiaocheng_20160127_fix1-2024.3.2.0.dist-info/top_level.txt
tutorialspoint_java_jishu_jiaocheng_20160127_fix1-2024.3.2.0.dist-info/RECORD
